jax_rocm7_plugin/_hybrid.so
jax_rocm7_plugin/_linalg.so
jax_rocm7_plugin/_prng.so
jax_rocm7_plugin/_rnn.so
jax_rocm7_plugin/_solver.so
jax_rocm7_plugin/_sparse.so
jax_rocm7_plugin/_triton.so
jax_rocm7_plugin/commit_info.py
jax_rocm7_plugin/rocm_plugin_extension.so
jax_rocm7_plugin/version.py
jax_rocm7_plugin-0.7.1.dist-info/METADATA
jax_rocm7_plugin-0.7.1.dist-info/WHEEL
jax_rocm7_plugin-0.7.1.dist-info/top_level.txt
jax_rocm7_plugin-0.7.1.dist-info/RECORD
